liblinear_multicore-2.50.0.dist-info/RECORD
liblinear_multicore-2.50.0.dist-info/WHEEL
liblinear_multicore-2.50.0.dist-info/top_level.txt
liblinear_multicore-2.50.0.dist-info/METADATA
liblinear_multicore-2.50.0.dist-info/licenses/LICENSE
liblinear/liblinear.py
liblinear/commonutil.py
liblinear/clib.cpython-314-darwin.so
liblinear/__init__.py
liblinear/liblinearutil.py
liblinear/.dylibs/libgomp.1.dylib
