Metadata-Version: 2.4
Name: liblinear-multicore
Version: 2.50.0
Summary: Python binding of multi-core LIBLINEAR
Home-page: https://www.csie.ntu.edu.tw/~cjlin/libsvmtools/multicore-liblinear
Author: ML group @ National Taiwan University
Author-email: cjlin@csie.ntu.edu.tw
License-File: LICENSE
Requires-Dist: scipy
Dynamic: author
Dynamic: author-email
Dynamic: description
Dynamic: description-content-type
Dynamic: home-page
Dynamic: license-file
Dynamic: requires-dist
Dynamic: summary
